wathq_mcp_server/__init__.py
wathq_mcp_server/server.py
wathq_mcp_server-0.1.0.dist-info/licenses/LICENSE
wathq_mcp_server-0.1.0.dist-info/METADATA
wathq_mcp_server-0.1.0.dist-info/WHEEL
wathq_mcp_server-0.1.0.dist-info/entry_points.txt
wathq_mcp_server-0.1.0.dist-info/top_level.txt
wathq_mcp_server-0.1.0.dist-info/RECORD
